pyimi/__init__.py
pyimi/assets.py
pyimi/devices.py
pyimi/directories.py
pyimi/exceptions.py
pyimi/imi.py
pyimi/profiles.py
pyimi-0.0.6.dist-info/LICENSE
pyimi-0.0.6.dist-info/METADATA
pyimi-0.0.6.dist-info/WHEEL
pyimi-0.0.6.dist-info/top_level.txt
pyimi-0.0.6.dist-info/RECORD
