Metadata-Version: 2.1
Name: pyimi
Version: 0.0.6
Summary: A python library for accessing IGEL's IMI
Home-page: https://github.com/mdmeacham/pyimi
Author: Mike Meacham
Author-email: mdmeacham@gmail.com
Classifier: Programming Language :: Python :: 3
Classifier: License :: OSI Approved :: MIT License
Classifier: Operating System :: OS Independent
License-File: LICENSE
